fact_checking/__init__.py
fact_checking/fact_checker.py
fact_checking/model.py
fact_checking/test.py
fact_checking/test_replicas.py
fact_checking/utils.py
fact_checking-0.0.3.dist-info/METADATA
fact_checking-0.0.3.dist-info/WHEEL
fact_checking-0.0.3.dist-info/top_level.txt
fact_checking-0.0.3.dist-info/RECORD
