Metadata-Version: 2.1
Name: fact-checking
Version: 0.0.3
Summary: Check a claim consistency against the provided evidence
Home-page: http://github.com/fractalego/fact_checking
Author: Alberto Cetoli
Author-email: alberto@nlulite.com
License: UNKNOWN
Platform: UNKNOWN
Classifier: License :: OSI Approved :: MIT License
Requires-Dist: numpy (==1.19.1)
Requires-Dist: transformers (==4.9.2)
Requires-Dist: torch (==1.9.0)
Requires-Dist: jupyterlab (==2.2.9)
